scanner/AWSSRP.py
scanner/__init__.py
scanner/scanner.py
scanner/utils.py
cognito_scanner-1.0.3.dist-info/LICENSE
cognito_scanner-1.0.3.dist-info/METADATA
cognito_scanner-1.0.3.dist-info/WHEEL
cognito_scanner-1.0.3.dist-info/entry_points.txt
cognito_scanner-1.0.3.dist-info/top_level.txt
cognito_scanner-1.0.3.dist-info/RECORD
